Workbook

Sheet README
B1: Türkiye · Tax Depreciation & Amortisation Model
B2: Supporting calculation file for the report to China Finance HQ
B4: Purpose | C4: Worked examples of depreciation (amortisman) and amortisation of intangibles under the Turkish Tax Procedure Law (Vergi Usul Kanunu, Law No. 213). Every figure is a live formula: change a yellow input cell and the schedules recalculate.
B5: Scope | C5: Tax book (VUK) treatment only. Statutory/IFRS book figures may differ; the gap is a temporary difference and is reconciled in the corporate tax return, not in this file.
B6: Currency | C6: Turkish Lira (TRY), unless stated otherwise.
B7: Tax year | C7: 2026 statutory thresholds. Thresholds are re-set every year by the Ministry of Treasury and Finance, so this file must be refreshed each January.
B8: Prepared | C8: September 2026
A10: How to read this file
B12: Cell style | C12: Meaning
B13: Yellow fill, blue bold text | C13: INPUT. Change these. Everything else recalculates.
B14: Black text | C14: Formula. Do not overwrite.
B15: Green text | C15: Formula linked to the Assumptions tab.
B16: Grey italic text | C16: Note, legal reference or source.
A18: Tabs
B20: Tab | C20: What it shows
B21: Assumptions | C21: All statutory thresholds and rates for 2026, each with its legal source. Every example reads from here.
B22: Ex1 Straight-Line | C22: Normal (straight-line) depreciation of machinery. The default method.
B23: Ex2 SL vs Declining | C23: Same asset under straight-line and declining-balance. Shows the timing benefit only.
B24: Ex3 Passenger Car | C24: The most error-prone case: 2026 expense caps plus pro-rata first-year depreciation. Two purchase structures compared.
B25: Ex4 Revaluation | C25: Optional revaluation under VUK Mük. 298/Ç and its effect on the depreciation base.
B26: Ex5 Intangibles | C26: Software, licences, leasehold improvements and goodwill.
B27: Sources | C27: Full legal references and links.
B29: IMPORTANT | C29: This file is a working model, not tax advice. Useful lives are set asset-by-asset and sector-by-sector in the official depreciation schedule (VUK General Communiqué No. 333 as amended). Confirm the rate for each specific asset against the current schedule before filing.

Sheet Assumptions
A1: Assumptions · 2026 statutory parameters
A3: A. Thresholds
A4: Parameter | B4: Value | C4: Unit | D4: Legal source
A5: Direct expensing threshold (below this, expense at once) | B5: 12000 | C5: TRY | D5: VUK Art. 313, final para. 2026 amount, VAT excluded. Assets forming one economic/technical unit are tested together.
A6: Passenger car: depreciable base cap, ÖTV+VAT excluded | B6: 1380000 | C6: TRY | D6: Income Tax Law Art. 40/7; 2026 amounts in Income Tax General Communiqué No. 332.
A7: Passenger car: depreciable base cap, ÖTV+VAT capitalised | B7: 2600000 | C7: TRY | D7: Income Tax Law Art. 40/7; applies also to second-hand purchases.
A8: Passenger car: ÖTV+VAT expensed directly, cap | B8: 1200000 | C8: TRY | D8: Income Tax Law Art. 40/1. Alternative to capitalising the taxes.
A9: Passenger car: monthly rental cap, VAT excluded | B9: 46000 | C9: TRY | D9: Income Tax Law Art. 40/5. Shown for completeness; not used in the examples.
A11: B. Methods and limits
A12: Parameter | B12: Value | C12: Unit | D12: Legal source
A13: Declining balance: multiple of normal rate | B13: 2 | C13: x | D13: VUK Repeated Art. 315. Balance-sheet taxpayers only.
A14: Declining balance: maximum rate | B14: 0.5 | C14: % | D14: VUK Repeated Art. 315. The doubled rate may never exceed 50%.
A15: Useful life: maximum multiple of the official life | B15: 2 | C15: x | D15: VUK Art. 320, as amended by Law No. 7338 (26.10.2021). A longer life may be elected, never a shorter one.
A16: Useful life: absolute ceiling | B16: 50 | C16: years | D16: VUK Art. 320. The elected life may not exceed 50 years.
A17: Goodwill and formation expenses: amortisation period | B17: 5 | C17: years | D17: VUK Art. 326. Equal instalments.
A18: Leasehold improvements: period if lease term unknown | B18: 5 | C18: years | D18: VUK Art. 327. Otherwise over the lease term, in equal percentages. Declining balance is not allowed.
A20: C. Indexation
A21: Parameter | B21: Value | C21: Unit | D21: Legal source
A22: Revaluation rate for 2025 (applied in 2026) | B22: 0.2549 | C22: % | D22: VUK General Communiqué No. 585, Official Gazette 27.11.2025. Based on the change in the domestic PPI (Yİ-ÜFE) to October.
A23: Inflation adjustment applied? (1 = yes, 0 = no) | B23: 0 | C23: flag | D23: VUK Provisional Art. 37, added by Law No. 7571 Art. 34, Official Gazette 25.12.2025 No. 33118. Inflation adjustment is suspended for 2025, 2026 and 2027 regardless of whether the statutory conditions are met.
A25: D. Representative useful lives
A26: Asset class | B26: Useful life (years) | C26: Rate | D26: Note
A27: Buildings (commercial / industrial, reinforced concrete) | B27: 50 | C27: =1/B27
A28: Computers and hardware | B28: 4 | C28: =1/B28
A29: Computer software | B29: 3 | C29: =1/B29
A30: Intangible rights (patents, know-how, licences) | B30: 15 | C30: =1/B30
A31: Passenger cars | B31: 5 | C31: =1/B31
A32: Office furniture and fixtures | B32: 5 | C32: =1/B32
A33: Machinery and equipment (varies widely by sector) | B33: 10 | C33: =1/B33
A34: Useful lives above are the commonly applied figures and are shown as a starting point only. The binding schedule is the Depreciation List annexed to VUK General Communiqué No. 333 (28.04.2004), as amended by Communiqués No. 339, 345, 365, 389, 399, 406, 418, 439 and 458. It runs to several hundred lines and is differentiated by sector: the same machine can carry a different life in two industries. Where an asset serves more than one sector, the longest life (lowest rate) applies.

Sheet Ex1 Straight-Line
A1: Example 1 · Normal (straight-line) depreciation — machinery
A2: Normal amortisman. VUK Art. 315. The default method: the same amount every year over the official useful life. Turkish tax depreciation is computed on full cost; no residual value is deducted.
A4: Inputs
A5: Acquisition cost (VAT excluded) | B5: 4800000
A6: Useful life (years) | B6: 10 | C6: ='Assumptions'!$B$33 | D6: ← official life from Assumptions
A7: Annual rate | B7: =1/$B$6
A8: Annual depreciation | B8: =$B$5*$B$7
A10: Schedule
A11: Year | B11: Opening NBV | C11: Depreciation | D11: Accumulated | E11: Closing NBV | G11: Check
A12: 1 | B12: =$B$5 | C12: =IF(A12>$B$6,0,MIN($B$5*$B$7,B12)) | D12: =IF(A12=1,C12,D11+C12) | E12: =B12-C12
A13: 2 | B13: =E12 | C13: =IF(A13>$B$6,0,MIN($B$5*$B$7,B13)) | D13: =IF(A13=1,C13,D12+C13) | E13: =B13-C13
A14: 3 | B14: =E13 | C14: =IF(A14>$B$6,0,MIN($B$5*$B$7,B14)) | D14: =IF(A14=1,C14,D13+C14) | E14: =B14-C14
A15: 4 | B15: =E14 | C15: =IF(A15>$B$6,0,MIN($B$5*$B$7,B15)) | D15: =IF(A15=1,C15,D14+C15) | E15: =B15-C15
A16: 5 | B16: =E15 | C16: =IF(A16>$B$6,0,MIN($B$5*$B$7,B16)) | D16: =IF(A16=1,C16,D15+C16) | E16: =B16-C16
A17: 6 | B17: =E16 | C17: =IF(A17>$B$6,0,MIN($B$5*$B$7,B17)) | D17: =IF(A17=1,C17,D16+C17) | E17: =B17-C17
A18: 7 | B18: =E17 | C18: =IF(A18>$B$6,0,MIN($B$5*$B$7,B18)) | D18: =IF(A18=1,C18,D17+C18) | E18: =B18-C18
A19: 8 | B19: =E18 | C19: =IF(A19>$B$6,0,MIN($B$5*$B$7,B19)) | D19: =IF(A19=1,C19,D18+C19) | E19: =B19-C19
A20: 9 | B20: =E19 | C20: =IF(A20>$B$6,0,MIN($B$5*$B$7,B20)) | D20: =IF(A20=1,C20,D19+C20) | E20: =B20-C20
A21: 10 | B21: =E20 | C21: =IF(A21>$B$6,0,MIN($B$5*$B$7,B21)) | D21: =IF(A21=1,C21,D20+C21) | E21: =B21-C21
A22: Total | C22: =SUM(C12:C21) | G22: =IF(ROUND(C22-$B$5,2)=0,"OK: fully depreciated","CHECK")
A24: Election available since Law No. 7338: the taxpayer may choose a longer life than the official one, up to twice that life and never beyond 50 years, applying the same rate each year (VUK Art. 320). A shorter life can never be elected. Since 2021 depreciation may also be computed on a daily basis (VUK Art. 320/A) instead of taking a full year in the year of acquisition.

Sheet Ex2 SL vs Declining
A1: Example 2 · Straight-line vs declining balance — same asset
A2: Azalan bakiyeler usulü. VUK Repeated Art. 315. The rate is twice the normal rate but capped at 50%, applied to the net book value each year. The balance remaining in the final year is written off in full. Available to balance-sheet taxpayers only. A taxpayer may switch from declining balance to straight-line, but never the other way.
A4: Inputs
A5: Cost | B5: 4800000
A6: Useful life | B6: 10
A7: Normal rate | B7: =1/$B$6
A8: Declining rate | B8: =MIN($B$7*'Assumptions'!$B$13,'Assumptions'!$B$14) | C8: min(2 × normal rate, 50%)
A10: Comparison
A11: Year | B11: SL depreciation | C11: SL accumulated | D11: SL closing NBV | F11: DB opening NBV | G11: DB depreciation | H11: DB closing NBV | J11: Difference (DB − SL)
A12: 1 | B12: =IF(A12>$B$6,0,$B$5*$B$7) | C12: =IF(A12=1,B12,C11+B12) | D12: =$B$5-C12 | F12: =$B$5 | G12: =IF(A12=$B$6,F12,F12*$B$8) | H12: =F12-G12 | J12: =G12-B12
A13: 2 | B13: =IF(A13>$B$6,0,$B$5*$B$7) | C13: =IF(A13=1,B13,C12+B13) | D13: =$B$5-C13 | F13: =H12 | G13: =IF(A13=$B$6,F13,F13*$B$8) | H13: =F13-G13 | J13: =G13-B13
A14: 3 | B14: =IF(A14>$B$6,0,$B$5*$B$7) | C14: =IF(A14=1,B14,C13+B14) | D14: =$B$5-C14 | F14: =H13 | G14: =IF(A14=$B$6,F14,F14*$B$8) | H14: =F14-G14 | J14: =G14-B14
A15: 4 | B15: =IF(A15>$B$6,0,$B$5*$B$7) | C15: =IF(A15=1,B15,C14+B15) | D15: =$B$5-C15 | F15: =H14 | G15: =IF(A15=$B$6,F15,F15*$B$8) | H15: =F15-G15 | J15: =G15-B15
A16: 5 | B16: =IF(A16>$B$6,0,$B$5*$B$7) | C16: =IF(A16=1,B16,C15+B16) | D16: =$B$5-C16 | F16: =H15 | G16: =IF(A16=$B$6,F16,F16*$B$8) | H16: =F16-G16 | J16: =G16-B16
A17: 6 | B17: =IF(A17>$B$6,0,$B$5*$B$7) | C17: =IF(A17=1,B17,C16+B17) | D17: =$B$5-C17 | F17: =H16 | G17: =IF(A17=$B$6,F17,F17*$B$8) | H17: =F17-G17 | J17: =G17-B17
A18: 7 | B18: =IF(A18>$B$6,0,$B$5*$B$7) | C18: =IF(A18=1,B18,C17+B18) | D18: =$B$5-C18 | F18: =H17 | G18: =IF(A18=$B$6,F18,F18*$B$8) | H18: =F18-G18 | J18: =G18-B18
A19: 8 | B19: =IF(A19>$B$6,0,$B$5*$B$7) | C19: =IF(A19=1,B19,C18+B19) | D19: =$B$5-C19 | F19: =H18 | G19: =IF(A19=$B$6,F19,F19*$B$8) | H19: =F19-G19 | J19: =G19-B19
A20: 9 | B20: =IF(A20>$B$6,0,$B$5*$B$7) | C20: =IF(A20=1,B20,C19+B20) | D20: =$B$5-C20 | F20: =H19 | G20: =IF(A20=$B$6,F20,F20*$B$8) | H20: =F20-G20 | J20: =G20-B20
A21: 10 | B21: =IF(A21>$B$6,0,$B$5*$B$7) | C21: =IF(A21=1,B21,C20+B21) | D21: =$B$5-C21 | F21: =H20 | G21: =IF(A21=$B$6,F21,F21*$B$8) | H21: =F21-G21 | J21: =G21-B21
A22: Total | B22: =SUM(B12:B21) | G22: =SUM(G12:G21) | J22: =SUM(J12:J21)
A23: Check | J23: =IF(ROUND(J22,2)=0,"OK: same total, different timing","CHECK")
A25: Both methods deduct the same total cost. Declining balance moves deductions forward, which is a cash-flow and net-present-value benefit, not a permanent tax saving. In a high-inflation and high-interest environment that timing benefit is economically significant.

Sheet Ex3 Passenger Car
A1: Example 3 · Passenger car — expense caps and pro-rata first year
A2: Passenger cars carry two restrictions that apply to no other asset: a cap on the deductible cost (Income Tax Law Art. 40/7 and 40/1) and pro-rata depreciation in the year of acquisition (VUK Art. 320). Depreciation on the portion above the cap is permanently non-deductible (kanunen kabul edilmeyen gider), so it is a permanent difference, not a timing difference.
A4: Inputs
A5: List price, ÖTV and VAT excluded | B5: 2000000
A6: ÖTV + VAT on the vehicle | B6: 1600000
A7: Month of acquisition (1 = January) | B7: 4
A8: Useful life (years) | B8: 5
A9: Months depreciated in year 1 | B9: =13-$B$7 | E9: Pro-rata rule: depreciation starts in the month of acquisition.
A11: Option A · ÖTV and VAT expensed directly
A12: Item | B12: Amount | C12: Deductible | E12: Basis
A13: ÖTV + VAT expensed in year 1 | B13: =$B$6 | C13: =MIN($B$6,'Assumptions'!$B$8) | E13: Cap: Income Tax Law Art. 40/1
A14: Depreciable cost | B14: =$B$5 | C14: =MIN($B$5,'Assumptions'!$B$6) | E14: Cap: Income Tax Law Art. 40/7, ÖTV+VAT excluded
A15: Disallowed cost (permanent difference) | B15: =MAX(0,$B$5-$C$14)+MAX(0,$B$6-$C$13)
A17: Option A · depreciation schedule
A18: Year | B18: Deductible depreciation | C18: Note
A19: 1 | B19: =$C$14/$B$8*$B$9/12 | C19: Pro-rata: part year only
A20: 2 | B20: =IF(A20>$B$8,0,$C$14/$B$8) | C20: Full year
A21: 3 | B21: =IF(A21>$B$8,0,$C$14/$B$8) | C21: Full year
A22: 4 | B22: =IF(A22>$B$8,0,$C$14/$B$8) | C22: Full year
A23: 5 | B23: =IF(A23>$B$8,0,$C$14/$B$8) | C23: Full year
A24: 6 | B24: =$C$14-SUM(B19:B23) | C24: Balance not taken in year 1 is deducted in the final year
A25: Total | B25: =SUM(B19:B24) | C25: =IF(ROUND(B25-$C$14,2)=0,"OK: equals capped base","CHECK")
A27: Option B · ÖTV and VAT capitalised into cost
A28: Item | B28: Amount | C28: Deductible | E28: Basis
A29: Total capitalised cost | B29: =$B$5+$B$6 | C29: =MIN($B$5+$B$6,'Assumptions'!$B$7) | E29: Cap: Income Tax Law Art. 40/7, taxes included
A30: Disallowed cost (permanent difference) | B30: =MAX(0,$B$5+$B$6-$C$29)
A32: Option B · depreciation schedule
A33: Year | B33: Deductible depreciation | C33: Note
A34: 1 | B34: =$C$29/$B$8*$B$9/12 | C34: Pro-rata: part year only
A35: 2 | B35: =IF(A35>$B$8,0,$C$29/$B$8) | C35: Full year
A36: 3 | B36: =IF(A36>$B$8,0,$C$29/$B$8) | C36: Full year
A37: 4 | B37: =IF(A37>$B$8,0,$C$29/$B$8) | C37: Full year
A38: 5 | B38: =IF(A38>$B$8,0,$C$29/$B$8) | C38: Full year
A39: 6 | B39: =$C$29-SUM(B34:B38) | C39: Balance deducted in the final year
A40: Total | B40: =SUM(B34:B39) | C40: =IF(ROUND(B40-$C$29,2)=0,"OK: equals capped base","CHECK")
A42: Which option deducts more?
A43: Option A: total deduction over life (incl. taxes expensed in year 1) | B43: =$B$25+$C$13
A44: Option B: total deduction over life | B44: =$B$40
A45: Advantage of A over B | B45: =B43-B44
A46: The choice is made once, at acquisition, and cannot be revisited. Option A also front-loads the deduction because the taxes are expensed immediately rather than spread over five years. Run both before buying: with the 2026 caps the answer changes with the price point.

Sheet Ex4 Revaluation
A1: Example 4 · Optional revaluation under VUK Repeated Art. 298/Ç
A2: Inflation adjustment is suspended for 2025, 2026 and 2027 (VUK Provisional Art. 37, added by Law No. 7571). In its place, taxpayers may elect to revalue depreciable assets each year by the official revaluation rate. The uplift is credited to a special fund in equity and is NOT taxed; depreciation is then computed on the revalued amount. This is the main mechanism protecting Turkish depreciation deductions from inflation.
A4: Inputs
A5: Original cost | B5: 4800000
A6: Accumulated depreciation before revaluation | B6: 1440000
A7: Useful life (years) | B7: 10
A8: Revaluation rate | B8: ='Assumptions'!$B$22 | E8: 2025 rate: 25.49% (VUK General Communiqué No. 585)
A10: Effect of the election
A11: Item | B11: Before | C11: After revaluation | E11: Note
A12: Gross cost | B12: =$B$5 | C12: =$B$5*(1+$B$8) | E12: Both cost and accumulated depreciation are indexed
A13: Accumulated depreciation | B13: =$B$6 | C13: =$B$6*(1+$B$8)
A14: Net book value | B14: =B12-B13 | C14: =C12-C13
A15: Increase credited to special fund (untaxed) | C15: =C14-B14 | E15: Shown in equity. Taxed only if distributed or withdrawn from the business.
A16: Annual depreciation from now on | B16: =$B$5/$B$7 | C16: =$C$12/$B$7
A17: Additional annual deduction | B17: =C16-B16
A19: Why this matters to a parent company: without revaluation, depreciation stays fixed in nominal lira while replacement cost rises with inflation, so the real value of the deduction erodes every year and taxable profit is overstated. The election is optional and must be assessed annually.

Sheet Ex5 Intangibles
A1: Example 5 · Intangibles, leasehold improvements and goodwill
A2: Classification drives the outcome here more than any calculation does. The same payment can be written off over 3 years or over 15 depending on whether it is treated as software or as a licence.
A4: Item | B4: Cost | C4: Period (years) | D4: Annual charge | E4: Legal basis and comment
A5: Computer software | B5: 900000 | C5: ='Assumptions'!$B$29 | D5: =B5/C5 | E5: Depreciation List item 4.3: 3 years. Purchased software, not a licence.
A6: Licence / intangible right | B6: 900000 | C6: ='Assumptions'!$B$30 | D6: =B6/C6 | E6: Patents, know-how, licences and similar rights: 15 years. Same cash outflow, five times the write-off period.
A7: Leasehold improvements (lease term known) | B7: 2400000 | C7: 8 | D7: =B7/C7 | E7: VUK Art. 327: over the lease term, in equal percentages. Declining balance is not permitted.
A8: Leasehold improvements (lease term unknown) | B8: 2400000 | C8: ='Assumptions'!$B$18 | D8: =B8/C8 | E8: VUK Art. 327: 5 years when the term is not fixed.
A9: Goodwill (peştemallık) | B9: 3000000 | C9: ='Assumptions'!$B$17 | D9: =B9/C9 | E9: VUK Art. 326: 5 years, equal instalments.
A10: Formation and organisation expenses | B10: 600000 | C10: ='Assumptions'!$B$17 | D10: =B10/C10 | E10: VUK Art. 326: 5 years, equal instalments. May alternatively be expensed as incurred.
A12: Software vs licence — the cost of misclassification
A13: Annual charge if treated as software | B13: =D5
A14: Annual charge if treated as a licence | B14: =D6
A15: Annual difference | B15: =B13-B14
A16: Both write off the same total cost, so this is a timing difference. In a high-inflation economy, however, deductions deferred by twelve years are worth a fraction of their nominal value. Classification should be documented at the point of purchase, in the contract wording, not decided later by the accounting team.

Sheet Sources
A1: Legal sources
A3: # | B3: Instrument | C3: Relevance
A4: 1 | B4: Tax Procedure Law No. 213 (VUK), Arts. 313–321 | C4: Definition of depreciable assets, the direct expensing threshold, normal depreciation, depreciation period and the pro-rata rule for passenger cars.
A5: 2 | B5: VUK Repeated Art. 315 | C5: Declining balance method; twice the normal rate, capped at 50%.
A6: 3 | B6: VUK Art. 320, as amended by Law No. 7338 (26.10.2021) | C6: Election of a longer useful life, up to twice the official life and never beyond 50 years.
A7: 4 | B7: VUK Art. 320/A, added by Law No. 7338 | C7: Option to compute depreciation on a daily basis.
A8: 5 | B8: VUK Art. 326 | C8: Goodwill and formation expenses: 5 years, equal instalments.
A9: 6 | B9: VUK Art. 327 | C9: Leasehold improvements: over the lease term in equal percentages; 5 years if the term is unknown.
A10: 7 | B10: VUK Repeated Art. 298/Ç | C10: Optional continuous revaluation of depreciable assets; the uplift is not taxed.
A11: 8 | B11: VUK Provisional Art. 37, added by Law No. 7571 Art. 34 | C11: Inflation adjustment suspended for 2025, 2026 and 2027. Official Gazette 25.12.2025, No. 33118. Extendable by Presidential decision for up to three further periods.
A12: 9 | B12: VUK General Communiqué No. 333 (28.04.2004), as amended by Nos. 339, 345, 365, 389, 399, 406, 418, 439, 458 | C12: The binding Depreciation List: useful lives and rates, asset by asset and sector by sector.
A13: 10 | B13: VUK General Communiqué No. 585 (Official Gazette 27.11.2025) | C13: 2025 revaluation rate: 25.49%.
A14: 11 | B14: Income Tax Law No. 193, Art. 40/1, 40/5 and 40/7 | C14: Passenger car expense restrictions: direct expense cap, rental cap and depreciable cost cap.
A15: 12 | B15: Income Tax General Communiqué No. 332 | C15: 2026 passenger car threshold amounts.
A17: Primary legislation is published in the Official Gazette (Resmî Gazete) and consolidated by the Revenue Administration (Gelir İdaresi Başkanlığı, gib.gov.tr). Threshold amounts are re-set annually; the figures in this file are the 2026 amounts and must be refreshed each January.
